wthell/__init__.py
wthell/__main__.py
wthell/instrument.py
wthell/main.py
wthell/wthell.py
wthell-0.2.1.dist-info/LICENSE
wthell-0.2.1.dist-info/METADATA
wthell-0.2.1.dist-info/WHEEL
wthell-0.2.1.dist-info/entry_points.txt
wthell-0.2.1.dist-info/top_level.txt
wthell-0.2.1.dist-info/RECORD
