Metadata-Version: 2.1
Name: wthell
Version: 0.2.1
Summary: A debugging tool that can help you what happened when you code quits unexpectedly
Home-page: https://github.com/gaogaotiantian/wthell
Author: Tian Gao
Author-email: gaogaotiantian@hotmail.com
License: UNKNOWN
Platform: UNKNOWN
Classifier: Development Status :: 3 - Alpha
Classifier: Programming Language :: Python :: 3
Classifier: License :: OSI Approved :: Apache Software License
Classifier: Operating System :: OS Independent
Requires-Dist: rich
